django_advanced_wallet/__init__.py
django_advanced_wallet/admin.py
django_advanced_wallet/app_settings.py
django_advanced_wallet/apps.py
django_advanced_wallet/errors.py
django_advanced_wallet/forms.py
django_advanced_wallet/managers.py
django_advanced_wallet/models.py
django_advanced_wallet/tests.py
django_advanced_wallet/views.py
django_advanced_wallet/migrations/0001_initial.py
django_advanced_wallet/migrations/__init__.py
django_advanced_wallet/templates/admin/django_advanced_wallet/form/new-operation.html
django_advanced_wallet-0.0.2.dist-info/LICENSE
django_advanced_wallet-0.0.2.dist-info/METADATA
django_advanced_wallet-0.0.2.dist-info/WHEEL
django_advanced_wallet-0.0.2.dist-info/top_level.txt
django_advanced_wallet-0.0.2.dist-info/RECORD
