Metadata-Version: 2.1
Name: django-advanced-wallet
Version: 0.0.2
Summary: An extensible wallet package for quick integration into your Django project.
Home-page: https://github.com/riquedev/django-advanced-wallet
Author: Henrique da Silva Santos
Author-email: henrique.santos@4u360.com.br
License: Apache License 2.0
Project-URL: Bug Tracker, https://github.com/riquedev/django-advanced-wallet/issues
Project-URL: Repository, https://github.com/riquedev/django-advanced-wallet
Keywords: wallet,framework,django
Classifier: Framework :: Django
Classifier: Development Status :: 4 - Beta
Classifier: Intended Audience :: Developers
Classifier: Programming Language :: Python :: 3
Requires-Python: >=3.7
License-File: LICENSE
Requires-Dist: Django (>=3.2.14)
Requires-Dist: django-extensions
